[
  {
    "Name": "CHUNKY DUNKY",
    "DateReleased": "MAY 2020",
    "Colorway": "White/Lagoon",
    "Price": "1200",
    "Line": "SB LOW",
    "URL": "https://i.postimg.cc/PqWzLLxR/CHUNKYDUNKY.png"
  },
  {
    "Name": "GRATEFUL DEAD",
    "DateReleased": "JULY 2020",
    "Colorway": "GREEN,YELLOW..",
    "Price": "2000",
    "Line": "DUNK LOW",
    "URL": "https://i.postimg.cc/xTXvvp8H/GRATEFULDEAD.png"
  },
  {
    "Name": "TRAVIS SCOTT",
    "DateReleased": "FEB 2020",
    "Colorway": "BEIGE/BLACK",
    "Price": "2200",
    "Line": "SB LOW",
    "URL": "https://i.postimg.cc/G2zFQZvP/TRAVISSCOTT.png"
  },
  {
    "Name": "STRANGE LOVE",
    "DateReleased": "FEB 2020",
    "Colorway": "BRIGHT MELON/PINK",
    "Price": "1400",
    "Line": "SB LOW",
    "URL": "https://i.postimg.cc/1RC0N1ms/STRANGELOVE.png"
  },
  {
    "Name": "STUSSY",
    "DateReleased": "JULY 2005",
    "Colorway": "SKY PINK/VANILLA",
    "Price": "2700",
    "Line": "SB LOW",
    "URL": "https://i.postimg.cc/sxNpF76v/STUSSY.png"
  },
  {
    "Name": "DIAMOND/TIFFANY",
    "DateReleased": "AUGUST 2005",
    "Colorway": "AQUA/CHROME",
    "Price": "3200",
    "Line": "SB LOW",
    "URL": "https://i.postimg.cc/N0cRwg47/TIFFANY.png"
  },
  {
    "Name": "BUCK",
    "DateReleased": "JANUARY 2004",
    "Colorway": "GREEN/DEL SOL",
    "Price": "1600",
    "Line": "SB LOW",
    "URL": "https://i.postimg.cc/Pf2yz84G/BUCK.png"
  },
  {
    "Name": "BLACK CEMENT",
    "DateReleased": "SEPTEMBER 2002",
    "Colorway": "BLACK CEMENT-GREY",
    "Price": "7000",
    "Line": "SB LOW",
    "URL": "https://i.postimg.cc/W3V8SGCV/BLACKCEMENT.png"
  }
]
